{
    "id": "2009_traffic_historical_context",
    "name": "Historical and Architectural Context for Traffic Management Needs Today",
    "description": "",
    "tags": [
        "policy",
        "trends",
        "overview"
    ],
    "presenters": [
        {
            "organizations": [],
            "venue": "FCC Technical Advisory Process Workshop",
            "date": "2009.12",
            "url": "",
            "person": "person:claffy__kc"
        }
    ],
    "links": [],
    "linkedObjects": "",
    "__typename": "media",
    "filename": "sources/media/2009_traffic_historical_context__pubdb.json",
    "pubdb_id": "presentation170",
    "resources": [
        {
            "name": "PDF",
            "url": "https://www.caida.org/publications/presentations/2009/traffic_historical_context/traffic_historical_context.pdf",
            "tags": []
        }
    ],
    "type": "PRESENTATION",
    "date": "2009.12"
}