{
    "id": "2017_packetlab_caidawide",
    "name": "PacketLab:A Universal Measurement Endpoint Interface",
    "description": "",
    "tags": [
        "measurement methodology",
        "security",
        "software/tools"
    ],
    "presenters": [
        {
            "organizations": [],
            "venue": "CAIDA-WIDE",
            "date": "2017.11",
            "url": "",
            "person": "person:Huffaker__Bradley"
        }
    ],
    "links": [
        {
            "to": "paper:2017_packetlab",
            "url": "https://www.caida.org/publications/papers/2017/packetlab/"
        }
    ],
    "linkedObjects": "",
    "__typename": "media",
    "filename": "sources/media/2017_packetlab_caidawide__pubdb.json",
    "pubdb_id": "presentation493",
    "resources": [
        {
            "name": "PDF",
            "url": "https://www.caida.org/publications/presentations/2017/packetlab_caidawide/packetlab_caidawide.pdf",
            "tags": []
        }
    ],
    "type": "PRESENTATION",
    "date": "2017.11"
}